odoo/addons/beesdoo_easy_my_coop/README.rst
odoo/addons/beesdoo_easy_my_coop/__init__.py
odoo/addons/beesdoo_easy_my_coop/__manifest__.py
odoo/addons/beesdoo_easy_my_coop/i18n/beesdoo_easy_my_coop.pot
odoo/addons/beesdoo_easy_my_coop/migrations/12.0.1.2.0/post-migrate.py
odoo/addons/beesdoo_easy_my_coop/readme/CONTRIBUTORS.rst
odoo/addons/beesdoo_easy_my_coop/readme/DESCRIPTION.rst
odoo/addons/beesdoo_easy_my_coop/static/description/index.html
odoo12_addon_beesdoo_easy_my_coop-12.0.1.2.2.dist-info/METADATA
odoo12_addon_beesdoo_easy_my_coop-12.0.1.2.2.dist-info/WHEEL
odoo12_addon_beesdoo_easy_my_coop-12.0.1.2.2.dist-info/top_level.txt
odoo12_addon_beesdoo_easy_my_coop-12.0.1.2.2.dist-info/RECORD
